moexr/client/__init__.py
moexr/client/client.py
moexr/client/error.py
moexr/client/properties.py
moexr/client/result.py
moexr_client-0.1.2.dist-info/WHEEL
moexr_client-0.1.2.dist-info/METADATA
moexr_client-0.1.2.dist-info/RECORD
